flask_libsass
