Metadata-Version: 1.1
Name: Flask-libsass
Version: 1.1.0
Summary: Flask extension for building css from sass or scss
Home-page: https://github.com/bwhmather/flask-libsass/
Author: Ben Mather
Author-email: bwhmather@bwhmather.com
License: BSD
Platform: any
Classifier: Environment :: Web Environment
Classifier: Framework :: Flask
Classifier: Intended Audience :: Developers
Classifier: License :: OSI Approved :: BSD License
Classifier: Operating System :: OS Independent
Classifier: Programming Language :: Python
Classifier: Topic :: Internet :: WWW/HTTP :: Dynamic Content
Classifier: Topic :: Software Development :: Libraries :: Python Modules
Classifier: Topic :: Software Development :: Compilers
